idtinc/__init__.py
idtinc/core/__init__.py
idtinc/core/message.py
idtinc/core/status.py
idtinc/firebase/__init__.py
idtinc/firebase/apps.py
idtinc/firebase/initialize.py
idtinc/firebase/message.py
idtinc/integration/__init__.py
idtinc/integration/apps.py
idtinc/integration/authentication.py
idtinc/integration/exception.py
idtinc/integration/middleware.py
idtinc/integration/paginator.py
idtinc/integration/response.py
idtinc/integration/serializers.py
idtinc/integration/service.py
idtinc/integration/swaggers.py
idtinc/integration/validators.py
idtinc/integration/views.py
idtinc/integration/decorators/__init__.py
idtinc/integration/decorators/method.py
idtinc/integration/decorators/singleton.py
idtinc/integration/helpers/__init__.py
idtinc/integration/helpers/query.py
idtinc/integration/helpers/string.py
idtinc/integration/helpers/timezone.py
idtinc/integration/helpers/zns.py
idtinc/integration/logging/__init__.py
idtinc/integration/logging/formatters.py
idtinc/integration/logging/setup.py
idtinc/integration/models/__init__.py
idtinc/integration/models/base.py
idtinc/integration/models/extra_fields.py
idtinc/integration/models/model_errors.py
idtinc/integration/storage/__init__.py
idtinc/integration/storage/backblaze.py
idtinc/integration/storage/minio.py
idtinc/integration/storage/staticfiles.py
idtinc-1.0.0.dist-info/METADATA
idtinc-1.0.0.dist-info/WHEEL
idtinc-1.0.0.dist-info/top_level.txt
idtinc-1.0.0.dist-info/RECORD
