Metadata-Version: 2.4
Name: idtinc
Version: 1.0.0
Summary: Idtinc Django & DRF Library
Author-email: Kiều Văn Chương <vanchuongkieu@gmail.com>
License: MIT
Requires-Python: >=3.9
Requires-Dist: Django>=3.2
Requires-Dist: requests>=2.31.0
Requires-Dist: djangorestframework>=3.14
Requires-Dist: drf-yasg>=1.21.7
Requires-Dist: minio>=7.1.2
Requires-Dist: django-currentuser>=0.9.0
Requires-Dist: django-cors-headers>=4.9.0
Requires-Dist: djangorestframework-simplejwt>=5.5.1
Provides-Extra: firebase
Requires-Dist: firebase-admin>=6.6.0; extra == "firebase"
